Workbook

Sheet Hypothèses
A1: POURACCORD — MODÈLE FINANCIER · Hypothèses & Paramètres
A3: Code couleur : Bleu = saisie manuelle | Fond jaune = hypothèse clé | Noir = formule calculée
A5: A — GRILLE DE PRIX (modifiable librement)
A6: Plan | B6: Dossiers inclus/mois | C6: Prix HT/mois (€) | D6: Prix/dossier inclus (€) | E6: Dossier supplémentaire (€) | F6: Mix % agences
A7: Starter | B7: 15 | C7: 149 | D7: =C7/B7 -> 9.9333333 | E7: 8 | F7: 0.5
A8: Pro | B8: 50 | C8: 349 | D8: =C8/B8 -> 6.98 | E8: 6 | F8: 0.35
A9: Expert | B9: 120 | C9: 699 | D9: =C9/B9 -> 5.825 | E9: 4 | F9: 0.15
E10: Somme mix → | F10: =SUM(F7:F9) -> 1
A12: B — CROISSANCE AGENCES
A13: Agences ajoutées / mois (M1–M6) | B13: 8
A14: Agences ajoutées / mois (M7–M12) | B14: 12
A15: Agences ajoutées / mois (M13–M24) | B15: 18
A16: Agences ajoutées / mois (M25–M36) | B16: 22
A17: Taux de churn mensuel (%) | B17: 0.05
A18: Taux conversion essai → payant (%) | B18: 0.1
A19: Durée essai gratuit (mois) | B19: 1
A21: C — COÛTS & UNIT ECONOMICS
A22: CAC — Coût acquisition agence (€) | B22: 1500
A23: Coût variable / dossier analysé (€) | B23: 0.15
A24: Charges fixes mensuelles (€) | B24: 8000
A25: % Charges fixes croissance/an | B25: 0.1
A26: ETP recrutés à M6 | B26: 2
A27: Coût moyen ETP/mois (€) | B27: 4500
A29: D — LOCATAIRES (effet réseau)
A30: Locataires inscrits M0 (base) | B30: 0
A31: Nouveaux locataires / mois (M1–M6) | B31: 600
A32: Nouveaux locataires / mois (M7–M12) | B32: 1500
A33: Nouveaux locataires / mois (M13–M36) | B33: 4000
A34: Nb de dossiers créés / locataire/mois | B34: 1.2
A36: E — ARPU PONDÉRÉ CALCULÉ (résultat)
A37: ARPU mensuel moyen pondéré (€) | B37: =SUMPRODUCT(C7:C9,F7:F9) -> 301.5
A38: Prix moyen par dossier (€) | B38: =SUMPRODUCT(D7:D9,F7:F9) -> 8.2834167

Sheet Projections Mensuelles
A1: PROJECTIONS MENSUELLES — 36 MOIS
A2: Toutes les formules sont liées à l'onglet Hypothèses. Modifie les hypothèses pour voir l'impact ici.
A3: ACTIVITÉ AGENCES
A4: Nouvelles agences (brutes) | B4: =Hypothèses!B13 -> 8 | C4: =Hypothèses!B13 -> 8 | D4: =Hypothèses!B13 -> 8 | E4: =Hypothèses!B13 -> 8 | F4: =Hypothèses!B13 -> 8 | G4: =Hypothèses!B13 -> 8 | H4: =Hypothèses!B14 -> 12 | I4: =Hypothèses!B14 -> 12 | J4: =Hypothèses!B14 -> 12 | K4: =Hypothèses!B14 -> 12 | L4: =Hypothèses!B14 -> 12 | M4: =Hypothèses!B14 -> 12 | N4: =Hypothèses!B15 -> 18 | O4: =Hypothèses!B15 -> 18 | P4: =Hypothèses!B15 -> 18 | Q4: =Hypothèses!B15 -> 18 | R4: =Hypothèses!B15 -> 18 | S4: =Hypothèses!B15 -> 18 | T4: =Hypothèses!B15 -> 18 | U4: =Hypothèses!B15 -> 18 | V4: =Hypothèses!B15 -> 18 | W4: =Hypothèses!B15 -> 18 | X4: =Hypothèses!B15 -> 18 | Y4: =Hypothèses!B15 -> 18 | Z4: =Hypothèses!B16 -> 22 | AA4: =Hypothèses!B16 -> 22 | AB4: =Hypothèses!B16 -> 22 | AC4: =Hypothèses!B16 -> 22 | AD4: =Hypothèses!B16 -> 22 | AE4: =Hypothèses!B16 -> 22 | AF4: =Hypothèses!B16 -> 22 | AG4: =Hypothèses!B16 -> 22 | AH4: =Hypothèses!B16 -> 22 | AI4: =Hypothèses!B16 -> 22 | AJ4: =Hypothèses!B16 -> 22 | AK4: =Hypothèses!B16 -> 22
A5: Agences perdues (churn) | B5: =0 -> 0 | C5: =ROUND(B6*Hypothèses!B17,0) -> 0 | D5: =ROUND(C6*Hypothèses!B17,0) -> 1 | E5: =ROUND(D6*Hypothèses!B17,0) -> 1 | F5: =ROUND(E6*Hypothèses!B17,0) -> 2 | G5: =ROUND(F6*Hypothèses!B17,0) -> 2 | H5: =ROUND(G6*Hypothèses!B17,0) -> 2 | I5: =ROUND(H6*Hypothèses!B17,0) -> 3 | J5: =ROUND(I6*Hypothèses!B17,0) -> 3 | K5: =ROUND(J6*Hypothèses!B17,0) -> 4 | L5: =ROUND(K6*Hypothèses!B17,0) -> 4 | M5: =ROUND(L6*Hypothèses!B17,0) -> 4 | N5: =ROUND(M6*Hypothèses!B17,0) -> 5 | O5: =ROUND(N6*Hypothèses!B17,0) -> 5 | P5: =ROUND(O6*Hypothèses!B17,0) -> 6 | Q5: =ROUND(P6*Hypothèses!B17,0) -> 7 | R5: =ROUND(Q6*Hypothèses!B17,0) -> 7 | S5: =ROUND(R6*Hypothèses!B17,0) -> 8 | T5: =ROUND(S6*Hypothèses!B17,0) -> 8 | U5: =ROUND(T6*Hypothèses!B17,0) -> 9 | V5: =ROUND(U6*Hypothèses!B17,0) -> 9 | W5: =ROUND(V6*Hypothèses!B17,0) -> 10 | X5: =ROUND(W6*Hypothèses!B17,0) -> 10 | Y5: =ROUND(X6*Hypothèses!B17,0) -> 10 | Z5: =ROUND(Y6*Hypothèses!B17,0) -> 11 | AA5: =ROUND(Z6*Hypothèses!B17,0) -> 11 | AB5: =ROUND(AA6*Hypothèses!B17,0) -> 12 | AC5: =ROUND(AB6*Hypothèses!B17,0) -> 12 | AD5: =ROUND(AC6*Hypothèses!B17,0) -> 13 | AE5: =ROUND(AD6*Hypothèses!B17,0) -> 13 | AF5: =ROUND(AE6*Hypothèses!B17,0) -> 14 | AG5: =ROUND(AF6*Hypothèses!B17,0) -> 14 | AH5: =ROUND(AG6*Hypothèses!B17,0) -> 15 | AI5: =ROUND(AH6*Hypothèses!B17,0) -> 15 | AJ5: =ROUND(AI6*Hypothèses!B17,0) -> 15 | AK5: =ROUND(AJ6*Hypothèses!B17,0) -> 16
A6: Agences payantes (cumulé) | B6: =B4-B5 -> 8 | C6: =MAX(0,B6+C4-C5) -> 16 | D6: =MAX(0,C6+D4-D5) -> 23 | E6: =MAX(0,D6+E4-E5) -> 30 | F6: =MAX(0,E6+F4-F5) -> 36 | G6: =MAX(0,F6+G4-G5) -> 42 | H6: =MAX(0,G6+H4-H5) -> 52 | I6: =MAX(0,H6+I4-I5) -> 61 | J6: =MAX(0,I6+J4-J5) -> 70 | ... AK6: =MAX(0,AJ6+AK4-AK5) -> 319
A7: REVENUS
A8: MRR (€) | B8: =B6*Hypothèses!B37 -> 2412 | C8: =C6*Hypothèses!B37 -> 4824 | D8: =D6*Hypothèses!B37 -> 6934.5 | E8: =E6*Hypothèses!B37 -> 9045 | F8: =F6*Hypothèses!B37 -> 10854 | G8: =G6*Hypothèses!B37 -> 12663 | H8: =H6*Hypothèses!B37 -> 15678 | I8: =I6*Hypothèses!B37 -> 18391.5 | J8: =J6*Hypothèses!B37 -> 21105 | K8: =K6*Hypothèses!B37 -> 23517 | L8: =L6*Hypothèses!B37 -> 25929 | M8: =M6*Hypothèses!B37 -> 28341 | N8: =N6*Hypothèses!B37 -> 32260.5 | O8: =O6*Hypothèses!B37 -> 36180 | P8: =P6*Hypothèses!B37 -> 39798 | Q8: =Q6*Hypothèses!B37 -> 43114.5 | R8: =R6*Hypothèses!B37 -> 46431 | S8: =S6*Hypothèses!B37 -> 49446 | T8: =T6*Hypothèses!B37 -> 52461 | U8: =U6*Hypothèses!B37 -> 55174.5 | V8: =V6*Hypothèses!B37 -> 57888 | W8: =W6*Hypothèses!B37 -> 60300 | X8: =X6*Hypothèses!B37 -> 62712 | Y8: =Y6*Hypothèses!B37 -> 65124 | Z8: =Z6*Hypothèses!B37 -> 68440.5 | AA8: =AA6*Hypothèses!B37 -> 71757 | AB8: =AB6*Hypothèses!B37 -> 74772 | AC8: =AC6*Hypothèses!B37 -> 77787 | AD8: =AD6*Hypothèses!B37 -> 80500.5 | AE8: =AE6*Hypothèses!B37 -> 83214 | AF8: =AF6*Hypothèses!B37 -> 85626 | AG8: =AG6*Hypothèses!B37 -> 88038 | AH8: =AH6*Hypothèses!B37 -> 90148.5 | AI8: =AI6*Hypothèses!B37 -> 92259 | AJ8: =AJ6*Hypothèses!B37 -> 94369.5 | AK8: =AK6*Hypothèses!B37 -> 96178.5
A9: ARR run-rate (€) | B9: =B8*12 -> 28944 | C9: =C8*12 -> 57888 | D9: =D8*12 -> 83214 | E9: =E8*12 -> 108540 | F9: =F8*12 -> 130248 | G9: =G8*12 -> 151956 | H9: =H8*12 -> 188136 | I9: =I8*12 -> 220698 | ... AK9: =AK8*12 -> 1154142
A11: Revenus dossiers supp. (€) | B11: =B8*0.1 -> 241.2 | C11: =C8*0.1 -> 482.4 | D11: =D8*0.1 -> 693.45 | E11: =E8*0.1 -> 904.5 | F11: =F8*0.1 -> 1085.4 | G11: =G8*0.1 -> 1266.3 | H11: =H8*0.1 -> 1567.8 | I11: =I8*0.1 -> 1839.15 | ... AK11: =AK8*0.1 -> 9617.85
A12: Revenus TOTAUX (€) | B12: =B8+B11 -> 2653.2 | C12: =C8+C11 -> 5306.4 | D12: =D8+D11 -> 7627.95 | E12: =E8+E11 -> 9949.5 | F12: =F8+F11 -> 11939.4 | G12: =G8+G11 -> 13929.3 | H12: =H8+H11 -> 17245.8 | I12: =I8+I11 -> 20230.65 | ... AK12: =AK8+AK11 -> 105796.35
A13: COÛTS
A14: Coût variable dossiers (€) | B14: =B6*(SUMPRODUCT(Hypothèses!B7:B9,Hypothèses!F7:F9))*Hypothèses!C23 -> 0 | C14: =C6*(SUMPRODUCT(Hypothèses!B7:B9,Hypothèses!F7:F9))*Hypothèses!C23 -> 0 | D14: =D6*(SUMPRODUCT(Hypothèses!B7:B9,Hypothèses!F7:F9))*Hypothèses!C23 -> 0 | E14: =E6*(SUMPRODUCT(Hypothèses!B7:B9,Hypothèses!F7:F9))*Hypothèses!C23 -> 0 | F14: =F6*(SUMPRODUCT(Hypothèses!B7:B9,Hypothèses!F7:F9))*Hypothèses!C23 -> 0 | G14: =G6*(SUMPRODUCT(Hypothèses!B7:B9,Hypothèses!F7:F9))*Hypothèses!C23 -> 0 | H14: =H6*(SUMPRODUCT(Hypothèses!B7:B9,Hypothèses!F7:F9))*Hypothèses!C23 -> 0 | I14: =I6*(SUMPRODUCT(Hypothèses!B7:B9,Hypothèses!F7:F9))*Hypothèses!C23 -> 0 | J14: =J6*(SUMPRODUCT(Hypothèses!B7:B9,Hypothèses!F7:F9))*Hypothèses!C23 -> 0 | K14: =K6*(SUMPRODUCT(Hypothèses!B7:B9,Hypothèses!F7:F9))*Hypothèses!C23 -> 0 | L14: =L6*(SUMPRODUCT(Hypothèses!B7:B9,Hypothèses!F7:F9))*Hypothèses!C23 -> 0 | M14: =M6*(SUMPRODUCT(Hypothèses!B7:B9,Hypothèses!F7:F9))*Hypothèses!C23 -> 0 | N14: =N6*(SUMPRODUCT(Hypothèses!B7:B9,Hypothèses!F7:F9))*Hypothèses!C23 -> 0 | O14: =O6*(SUMPRODUCT(Hypothèses!B7:B9,Hypothèses!F7:F9))*Hypothèses!C23 -> 0 | P14: =P6*(SUMPRODUCT(Hypothèses!B7:B9,Hypothèses!F7:F9))*Hypothèses!C23 -> 0 | Q14: =Q6*(SUMPRODUCT(Hypothèses!B7:B9,Hypothèses!F7:F9))*Hypothèses!C23 -> 0 | R14: =R6*(SUMPRODUCT(Hypothèses!B7:B9,Hypothèses!F7:F9))*Hypothèses!C23 -> 0 | S14: =S6*(SUMPRODUCT(Hypothèses!B7:B9,Hypothèses!F7:F9))*Hypothèses!C23 -> 0 | T14: =T6*(SUMPRODUCT(Hypothèses!B7:B9,Hypothèses!F7:F9))*Hypothèses!C23 -> 0 | U14: =U6*(SUMPRODUCT(Hypothèses!B7:B9,Hypothèses!F7:F9))*Hypothèses!C23 -> 0 | V14: =V6*(SUMPRODUCT(Hypothèses!B7:B9,Hypothèses!F7:F9))*Hypothèses!C23 -> 0 | W14: =W6*(SUMPRODUCT(Hypothèses!B7:B9,Hypothèses!F7:F9))*Hypothèses!C23 -> 0 | X14: =X6*(SUMPRODUCT(Hypothèses!B7:B9,Hypothèses!F7:F9))*Hypothèses!C23 -> 0 | Y14: =Y6*(SUMPRODUCT(Hypothèses!B7:B9,Hypothèses!F7:F9))*Hypothèses!C23 -> 0 | Z14: =Z6*(SUMPRODUCT(Hypothèses!B7:B9,Hypothèses!F7:F9))*Hypothèses!C23 -> 0 | AA14: =AA6*(SUMPRODUCT(Hypothèses!B7:B9,Hypothèses!F7:F9))*Hypothèses!C23 -> 0 | AB14: =AB6*(SUMPRODUCT(Hypothèses!B7:B9,Hypothèses!F7:F9))*Hypothèses!C23 -> 0 | AC14: =AC6*(SUMPRODUCT(Hypothèses!B7:B9,Hypothèses!F7:F9))*Hypothèses!C23 -> 0 | AD14: =AD6*(SUMPRODUCT(Hypothèses!B7:B9,Hypothèses!F7:F9))*Hypothèses!C23 -> 0 | AE14: =AE6*(SUMPRODUCT(Hypothèses!B7:B9,Hypothèses!F7:F9))*Hypothèses!C23 -> 0 | AF14: =AF6*(SUMPRODUCT(Hypothèses!B7:B9,Hypothèses!F7:F9))*Hypothèses!C23 -> 0 | AG14: =AG6*(SUMPRODUCT(Hypothèses!B7:B9,Hypothèses!F7:F9))*Hypothèses!C23 -> 0 | AH14: =AH6*(SUMPRODUCT(Hypothèses!B7:B9,Hypothèses!F7:F9))*Hypothèses!C23 -> 0 | AI14: =AI6*(SUMPRODUCT(Hypothèses!B7:B9,Hypothèses!F7:F9))*Hypothèses!C23 -> 0 | AJ14: =AJ6*(SUMPRODUCT(Hypothèses!B7:B9,Hypothèses!F7:F9))*Hypothèses!C23 -> 0 | AK14: =AK6*(SUMPRODUCT(Hypothèses!B7:B9,Hypothèses!F7:F9))*Hypothèses!C23 -> 0
A15: Charges fixes (€) | B15: =Hypothèses!C24*(1+Hypothèses!C25)^0 -> 0 | C15: =Hypothèses!C24*(1+Hypothèses!C25)^0 -> 0 | D15: =Hypothèses!C24*(1+Hypothèses!C25)^0 -> 0 | E15: =Hypothèses!C24*(1+Hypothèses!C25)^0 -> 0 | F15: =Hypothèses!C24*(1+Hypothèses!C25)^0 -> 0 | G15: =Hypothèses!C24*(1+Hypothèses!C25)^0 -> 0 | H15: =Hypothèses!C24*(1+Hypothèses!C25)^0 -> 0 | I15: =Hypothèses!C24*(1+Hypothèses!C25)^0 -> 0 | J15: =Hypothèses!C24*(1+Hypothèses!C25)^0 -> 0 | K15: =Hypothèses!C24*(1+Hypothèses!C25)^0 -> 0 | L15: =Hypothèses!C24*(1+Hypothèses!C25)^0 -> 0 | M15: =Hypothèses!C24*(1+Hypothèses!C25)^0 -> 0 | N15: =Hypothèses!C24*(1+Hypothèses!C25)^1 -> 0 | O15: =Hypothèses!C24*(1+Hypothèses!C25)^1 -> 0 | P15: =Hypothèses!C24*(1+Hypothèses!C25)^1 -> 0 | Q15: =Hypothèses!C24*(1+Hypothèses!C25)^1 -> 0 | R15: =Hypothèses!C24*(1+Hypothèses!C25)^1 -> 0 | S15: =Hypothèses!C24*(1+Hypothèses!C25)^1 -> 0 | T15: =Hypothèses!C24*(1+Hypothèses!C25)^1 -> 0 | U15: =Hypothèses!C24*(1+Hypothèses!C25)^1 -> 0 | V15: =Hypothèses!C24*(1+Hypothèses!C25)^1 -> 0 | W15: =Hypothèses!C24*(1+Hypothèses!C25)^1 -> 0 | X15: =Hypothèses!C24*(1+Hypothèses!C25)^1 -> 0 | Y15: =Hypothèses!C24*(1+Hypothèses!C25)^1 -> 0 | Z15: =Hypothèses!C24*(1+Hypothèses!C25)^2 -> 0 | AA15: =Hypothèses!C24*(1+Hypothèses!C25)^2 -> 0 | AB15: =Hypothèses!C24*(1+Hypothèses!C25)^2 -> 0 | AC15: =Hypothèses!C24*(1+Hypothèses!C25)^2 -> 0 | AD15: =Hypothèses!C24*(1+Hypothèses!C25)^2 -> 0 | AE15: =Hypothèses!C24*(1+Hypothèses!C25)^2 -> 0 | AF15: =Hypothèses!C24*(1+Hypothèses!C25)^2 -> 0 | AG15: =Hypothèses!C24*(1+Hypothèses!C25)^2 -> 0 | AH15: =Hypothèses!C24*(1+Hypothèses!C25)^2 -> 0 | AI15: =Hypothèses!C24*(1+Hypothèses!C25)^2 -> 0 | AJ15: =Hypothèses!C24*(1+Hypothèses!C25)^2 -> 0 | AK15: =Hypothèses!C24*(1+Hypothèses!C25)^2 -> 0
A16: CAC (acquisition) (€) | B16: =B4*Hypothèses!C22 -> 0 | C16: =C4*Hypothèses!C22 -> 0 | D16: =D4*Hypothèses!C22 -> 0 | E16: =E4*Hypothèses!C22 -> 0 | F16: =F4*Hypothèses!C22 -> 0 | G16: =G4*Hypothèses!C22 -> 0 | H16: =H4*Hypothèses!C22 -> 0 | I16: =I4*Hypothèses!C22 -> 0 | J16: =J4*Hypothèses!C22 -> 0 | K16: =K4*Hypothèses!C22 -> 0 | L16: =L4*Hypothèses!C22 -> 0 | M16: =M4*Hypothèses!C22 -> 0 | N16: =N4*Hypothèses!C22 -> 0 | O16: =O4*Hypothèses!C22 -> 0 | P16: =P4*Hypothèses!C22 -> 0 | Q16: =Q4*Hypothèses!C22 -> 0 | R16: =R4*Hypothèses!C22 -> 0 | S16: =S4*Hypothèses!C22 -> 0 | T16: =T4*Hypothèses!C22 -> 0 | U16: =U4*Hypothèses!C22 -> 0 | V16: =V4*Hypothèses!C22 -> 0 | W16: =W4*Hypothèses!C22 -> 0 | X16: =X4*Hypothèses!C22 -> 0 | Y16: =Y4*Hypothèses!C22 -> 0 | Z16: =Z4*Hypothèses!C22 -> 0 | AA16: =AA4*Hypothèses!C22 -> 0 | AB16: =AB4*Hypothèses!C22 -> 0 | AC16: =AC4*Hypothèses!C22 -> 0 | AD16: =AD4*Hypothèses!C22 -> 0 | AE16: =AE4*Hypothèses!C22 -> 0 | AF16: =AF4*Hypothèses!C22 -> 0 | AG16: =AG4*Hypothèses!C22 -> 0 | AH16: =AH4*Hypothèses!C22 -> 0 | AI16: =AI4*Hypothèses!C22 -> 0 | AJ16: =AJ4*Hypothèses!C22 -> 0 | AK16: =AK4*Hypothèses!C22 -> 0
A17: Masse salariale (€) | B17: =0 -> 0 | C17: =0 -> 0 | D17: =0 -> 0 | E17: =0 -> 0 | F17: =0 -> 0 | G17: =Hypothèses!C26*Hypothèses!C27 -> 0 | H17: =Hypothèses!C26*Hypothèses!C27 -> 0 | I17: =Hypothèses!C26*Hypothèses!C27 -> 0 | J17: =Hypothèses!C26*Hypothèses!C27 -> 0 | K17: =Hypothèses!C26*Hypothèses!C27 -> 0 | L17: =Hypothèses!C26*Hypothèses!C27 -> 0 | M17: =Hypothèses!C26*Hypothèses!C27 -> 0 | N17: =Hypothèses!C26*Hypothèses!C27 -> 0 | O17: =Hypothèses!C26*Hypothèses!C27 -> 0 | P17: =Hypothèses!C26*Hypothèses!C27 -> 0 | Q17: =Hypothèses!C26*Hypothèses!C27 -> 0 | R17: =Hypothèses!C26*Hypothèses!C27 -> 0 | S17: =Hypothèses!C26*Hypothèses!C27 -> 0 | T17: =Hypothèses!C26*Hypothèses!C27 -> 0 | U17: =Hypothèses!C26*Hypothèses!C27 -> 0 | V17: =Hypothèses!C26*Hypothèses!C27 -> 0 | W17: =Hypothèses!C26*Hypothèses!C27 -> 0 | X17: =Hypothèses!C26*Hypothèses!C27 -> 0 | Y17: =Hypothèses!C26*Hypothèses!C27 -> 0 | Z17: =Hypothèses!C26*Hypothèses!C27 -> 0 | AA17: =Hypothèses!C26*Hypothèses!C27 -> 0 | AB17: =Hypothèses!C26*Hypothèses!C27 -> 0 | AC17: =Hypothèses!C26*Hypothèses!C27 -> 0 | AD17: =Hypothèses!C26*Hypothèses!C27 -> 0 | AE17: =Hypothèses!C26*Hypothèses!C27 -> 0 | AF17: =Hypothèses!C26*Hypothèses!C27 -> 0 | AG17: =Hypothèses!C26*Hypothèses!C27 -> 0 | AH17: =Hypothèses!C26*Hypothèses!C27 -> 0 | AI17: =Hypothèses!C26*Hypothèses!C27 -> 0 | AJ17: =Hypothèses!C26*Hypothèses!C27 -> 0 | AK17: =Hypothèses!C26*Hypothèses!C27 -> 0
A18: TOTAL COÛTS (€) | B18: =SUM(B14:B17) -> 0 | C18: =SUM(C14:C17) -> 0 | D18: =SUM(D14:D17) -> 0 | E18: =SUM(E14:E17) -> 0 | F18: =SUM(F14:F17) -> 0 | G18: =SUM(G14:G17) -> 0 | H18: =SUM(H14:H17) -> 0 | I18: =SUM(I14:I17) -> 0 | ... AK18: =SUM(AK14:AK17) -> 0
A19: RENTABILITÉ
A20: EBITDA (€) | B20: =B12-B18 -> 2653.2 | C20: =C12-C18 -> 5306.4 | D20: =D12-D18 -> 7627.95 | E20: =E12-E18 -> 9949.5 | F20: =F12-F18 -> 11939.4 | G20: =G12-G18 -> 13929.3 | H20: =H12-H18 -> 17245.8 | I20: =I12-I18 -> 20230.65 | ... AK20: =AK12-AK18 -> 105796.35
A21: Marge EBITDA (%) | B21: =IF(B12>0,B20/B12,"") -> 1 | C21: =IF(C12>0,C20/C12,"") -> 1 | D21: =IF(D12>0,D20/D12,"") -> 1 | E21: =IF(E12>0,E20/E12,"") -> 1 | F21: =IF(F12>0,F20/F12,"") -> 1 | G21: =IF(G12>0,G20/G12,"") -> 1 | H21: =IF(H12>0,H20/H12,"") -> 1 | I21: =IF(I12>0,I20/I12,"") -> 1 | ... AK21: =IF(AK12>0,AK20/AK12,"") -> 1
A22: MÉTRIQUES
A23: Locataires inscrits (cumulé) | B23: =Hypothèses!B30+Hypothèses!B31 -> 600 | C23: =B23+Hypothèses!B31 -> 1200 | D23: =C23+Hypothèses!B31 -> 1800 | E23: =D23+Hypothèses!B31 -> 2400 | F23: =E23+Hypothèses!B31 -> 3000 | G23: =F23+Hypothèses!B31 -> 3600 | H23: =G23+Hypothèses!B32 -> 5100 | I23: =H23+Hypothèses!B32 -> 6600 | J23: =I23+Hypothèses!B32 -> 8100 | K23: =J23+Hypothèses!B32 -> 9600 | L23: =K23+Hypothèses!B32 -> 11100 | M23: =L23+Hypothèses!B32 -> 12600 | N23: =M23+Hypothèses!B33 -> 16600 | O23: =N23+Hypothèses!B33 -> 20600 | P23: =O23+Hypothèses!B33 -> 24600 | Q23: =P23+Hypothèses!B33 -> 28600 | R23: =Q23+Hypothèses!B33 -> 32600 | S23: =R23+Hypothèses!B33 -> 36600 | T23: =S23+Hypothèses!B33 -> 40600 | U23: =T23+Hypothèses!B33 -> 44600 | V23: =U23+Hypothèses!B33 -> 48600 | W23: =V23+Hypothèses!B33 -> 52600 | X23: =W23+Hypothèses!B33 -> 56600 | Y23: =X23+Hypothèses!B33 -> 60600 | Z23: =Y23+Hypothèses!B33 -> 64600 | AA23: =Z23+Hypothèses!B33 -> 68600 | AB23: =AA23+Hypothèses!B33 -> 72600 | AC23: =AB23+Hypothèses!B33 -> 76600 | AD23: =AC23+Hypothèses!B33 -> 80600 | AE23: =AD23+Hypothèses!B33 -> 84600 | AF23: =AE23+Hypothèses!B33 -> 88600 | AG23: =AF23+Hypothèses!B33 -> 92600 | AH23: =AG23+Hypothèses!B33 -> 96600 | AI23: =AH23+Hypothèses!B33 -> 100600 | AJ23: =AI23+Hypothèses!B33 -> 104600 | AK23: =AJ23+Hypothèses!B33 -> 108600
A24: Dossiers créés / mois | B24: =B23*Hypothèses!B34 -> 720 | C24: =C23*Hypothèses!B34 -> 1440 | D24: =D23*Hypothèses!B34 -> 2160 | E24: =E23*Hypothèses!B34 -> 2880 | F24: =F23*Hypothèses!B34 -> 3600 | G24: =G23*Hypothèses!B34 -> 4320 | H24: =H23*Hypothèses!B34 -> 6120 | I24: =I23*Hypothèses!B34 -> 7920 | J24: =J23*Hypothèses!B34 -> 9720 | K24: =K23*Hypothèses!B34 -> 11520 | L24: =L23*Hypothèses!B34 -> 13320 | M24: =M23*Hypothèses!B34 -> 15120 | N24: =N23*Hypothèses!B34 -> 19920 | O24: =O23*Hypothèses!B34 -> 24720 | P24: =P23*Hypothèses!B34 -> 29520 | Q24: =Q23*Hypothèses!B34 -> 34320 | R24: =R23*Hypothèses!B34 -> 39120 | S24: =S23*Hypothèses!B34 -> 43920 | T24: =T23*Hypothèses!B34 -> 48720 | U24: =U23*Hypothèses!B34 -> 53520 | V24: =V23*Hypothèses!B34 -> 58320 | W24: =W23*Hypothèses!B34 -> 63120 | X24: =X23*Hypothèses!B34 -> 67920 | Y24: =Y23*Hypothèses!B34 -> 72720 | Z24: =Z23*Hypothèses!B34 -> 77520 | AA24: =AA23*Hypothèses!B34 -> 82320 | AB24: =AB23*Hypothèses!B34 -> 87120 | AC24: =AC23*Hypothèses!B34 -> 91920 | AD24: =AD23*Hypothèses!B34 -> 96720 | AE24: =AE23*Hypothèses!B34 -> 101520 | AF24: =AF23*Hypothèses!B34 -> 106320 | AG24: =AG23*Hypothèses!B34 -> 111120 | AH24: =AH23*Hypothèses!B34 -> 115920 | AI24: =AI23*Hypothèses!B34 -> 120720 | AJ24: =AJ23*Hypothèses!B34 -> 125520 | AK24: =AK23*Hypothèses!B34 -> 130320
A25: LTV estimée / agence (€) | B25: =IF(Hypothèses!B17>0,Hypothèses!B37/Hypothèses!B17,0) -> 6030 | C25: =IF(Hypothèses!B17>0,Hypothèses!B37/Hypothèses!B17,0) -> 6030 | D25: =IF(Hypothèses!B17>0,Hypothèses!B37/Hypothèses!B17,0) -> 6030 | E25: =IF(Hypothèses!B17>0,Hypothèses!B37/Hypothèses!B17,0) -> 6030 | F25: =IF(Hypothèses!B17>0,Hypothèses!B37/Hypothèses!B17,0) -> 6030 | G25: =IF(Hypothèses!B17>0,Hypothèses!B37/Hypothèses!B17,0) -> 6030 | H25: =IF(Hypothèses!B17>0,Hypothèses!B37/Hypothèses!B17,0) -> 6030 | I25: =IF(Hypothèses!B17>0,Hypothèses!B37/Hypothèses!B17,0) -> 6030 | J25: =IF(Hypothèses!B17>0,Hypothèses!B37/Hypothèses!B17,0) -> 6030 | K25: =IF(Hypothèses!B17>0,Hypothèses!B37/Hypothèses!B17,0) -> 6030 | L25: =IF(Hypothèses!B17>0,Hypothèses!B37/Hypothèses!B17,0) -> 6030 | M25: =IF(Hypothèses!B17>0,Hypothèses!B37/Hypothèses!B17,0) -> 6030 | N25: =IF(Hypothèses!B17>0,Hypothèses!B37/Hypothèses!B17,0) -> 6030 | O25: =IF(Hypothèses!B17>0,Hypothèses!B37/Hypothèses!B17,0) -> 6030 | P25: =IF(Hypothèses!B17>0,Hypothèses!B37/Hypothèses!B17,0) -> 6030 | Q25: =IF(Hypothèses!B17>0,Hypothèses!B37/Hypothèses!B17,0) -> 6030 | R25: =IF(Hypothèses!B17>0,Hypothèses!B37/Hypothèses!B17,0) -> 6030 | S25: =IF(Hypothèses!B17>0,Hypothèses!B37/Hypothèses!B17,0) -> 6030 | T25: =IF(Hypothèses!B17>0,Hypothèses!B37/Hypothèses!B17,0) -> 6030 | U25: =IF(Hypothèses!B17>0,Hypothèses!B37/Hypothèses!B17,0) -> 6030 | V25: =IF(Hypothèses!B17>0,Hypothèses!B37/Hypothèses!B17,0) -> 6030 | W25: =IF(Hypothèses!B17>0,Hypothèses!B37/Hypothèses!B17,0) -> 6030 | X25: =IF(Hypothèses!B17>0,Hypothèses!B37/Hypothèses!B17,0) -> 6030 | Y25: =IF(Hypothèses!B17>0,Hypothèses!B37/Hypothèses!B17,0) -> 6030 | Z25: =IF(Hypothèses!B17>0,Hypothèses!B37/Hypothèses!B17,0) -> 6030 | AA25: =IF(Hypothèses!B17>0,Hypothèses!B37/Hypothèses!B17,0) -> 6030 | AB25: =IF(Hypothèses!B17>0,Hypothèses!B37/Hypothèses!B17,0) -> 6030 | AC25: =IF(Hypothèses!B17>0,Hypothèses!B37/Hypothèses!B17,0) -> 6030 | AD25: =IF(Hypothèses!B17>0,Hypothèses!B37/Hypothèses!B17,0) -> 6030 | AE25: =IF(Hypothèses!B17>0,Hypothèses!B37/Hypothèses!B17,0) -> 6030 | AF25: =IF(Hypothèses!B17>0,Hypothèses!B37/Hypothèses!B17,0) -> 6030 | AG25: =IF(Hypothèses!B17>0,Hypothèses!B37/Hypothèses!B17,0) -> 6030 | AH25: =IF(Hypothèses!B17>0,Hypothèses!B37/Hypothèses!B17,0) -> 6030 | AI25: =IF(Hypothèses!B17>0,Hypothèses!B37/Hypothèses!B17,0) -> 6030 | AJ25: =IF(Hypothèses!B17>0,Hypothèses!B37/Hypothèses!B17,0) -> 6030 | AK25: =IF(Hypothèses!B17>0,Hypothèses!B37/Hypothèses!B17,0) -> 6030
A26: LTV / CAC | B26: =IF(Hypothèses!C22>0,B25/Hypothèses!C22,0) -> 0 | C26: =IF(Hypothèses!C22>0,C25/Hypothèses!C22,0) -> 0 | D26: =IF(Hypothèses!C22>0,D25/Hypothèses!C22,0) -> 0 | E26: =IF(Hypothèses!C22>0,E25/Hypothèses!C22,0) -> 0 | F26: =IF(Hypothèses!C22>0,F25/Hypothèses!C22,0) -> 0 | G26: =IF(Hypothèses!C22>0,G25/Hypothèses!C22,0) -> 0 | H26: =IF(Hypothèses!C22>0,H25/Hypothèses!C22,0) -> 0 | I26: =IF(Hypothèses!C22>0,I25/Hypothèses!C22,0) -> 0 | J26: =IF(Hypothèses!C22>0,J25/Hypothèses!C22,0) -> 0 | K26: =IF(Hypothèses!C22>0,K25/Hypothèses!C22,0) -> 0 | L26: =IF(Hypothèses!C22>0,L25/Hypothèses!C22,0) -> 0 | M26: =IF(Hypothèses!C22>0,M25/Hypothèses!C22,0) -> 0 | N26: =IF(Hypothèses!C22>0,N25/Hypothèses!C22,0) -> 0 | O26: =IF(Hypothèses!C22>0,O25/Hypothèses!C22,0) -> 0 | P26: =IF(Hypothèses!C22>0,P25/Hypothèses!C22,0) -> 0 | Q26: =IF(Hypothèses!C22>0,Q25/Hypothèses!C22,0) -> 0 | R26: =IF(Hypothèses!C22>0,R25/Hypothèses!C22,0) -> 0 | S26: =IF(Hypothèses!C22>0,S25/Hypothèses!C22,0) -> 0 | T26: =IF(Hypothèses!C22>0,T25/Hypothèses!C22,0) -> 0 | U26: =IF(Hypothèses!C22>0,U25/Hypothèses!C22,0) -> 0 | V26: =IF(Hypothèses!C22>0,V25/Hypothèses!C22,0) -> 0 | W26: =IF(Hypothèses!C22>0,W25/Hypothèses!C22,0) -> 0 | X26: =IF(Hypothèses!C22>0,X25/Hypothèses!C22,0) -> 0 | Y26: =IF(Hypothèses!C22>0,Y25/Hypothèses!C22,0) -> 0 | Z26: =IF(Hypothèses!C22>0,Z25/Hypothèses!C22,0) -> 0 | AA26: =IF(Hypothèses!C22>0,AA25/Hypothèses!C22,0) -> 0 | AB26: =IF(Hypothèses!C22>0,AB25/Hypothèses!C22,0) -> 0 | AC26: =IF(Hypothèses!C22>0,AC25/Hypothèses!C22,0) -> 0 | AD26: =IF(Hypothèses!C22>0,AD25/Hypothèses!C22,0) -> 0 | AE26: =IF(Hypothèses!C22>0,AE25/Hypothèses!C22,0) -> 0 | AF26: =IF(Hypothèses!C22>0,AF25/Hypothèses!C22,0) -> 0 | AG26: =IF(Hypothèses!C22>0,AG25/Hypothèses!C22,0) -> 0 | AH26: =IF(Hypothèses!C22>0,AH25/Hypothèses!C22,0) -> 0 | AI26: =IF(Hypothèses!C22>0,AI25/Hypothèses!C22,0) -> 0 | AJ26: =IF(Hypothèses!C22>0,AJ25/Hypothèses!C22,0) -> 0 | AK26: =IF(Hypothèses!C22>0,AK25/Hypothèses!C22,0) -> 0

Sheet Synthèse Annuelle
A1: SYNTHÈSE ANNUELLE — AN 1 / AN 2 / AN 3
A3: Indicateur | B3: AN 1 (M1–M12) | C3: AN 2 (M13–M24) | D3: AN 3 (M25–M36)
A4: Agences payantes fin de période | B4: =MAX('Projections Mensuelles'!B6:M6) -> 94 | C4: =MAX('Projections Mensuelles'!N6:Y6) -> 216 | D4: =MAX('Projections Mensuelles'!Z6:AK6) -> 319
A5: Nouvelles agences (brutes) | B5: =SUM('Projections Mensuelles'!B4:M4) -> 120 | C5: =SUM('Projections Mensuelles'!N4:Y4) -> 216 | D5: =SUM('Projections Mensuelles'!Z4:AK4) -> 264
A6: MRR fin de période (€) | B6: =MAX('Projections Mensuelles'!B8:M8) -> 28341 | C6: =MAX('Projections Mensuelles'!N8:Y8) -> 65124 | D6: =MAX('Projections Mensuelles'!Z8:AK8) -> 96178.5
A7: ARR run-rate fin de période (€) | B7: =MAX('Projections Mensuelles'!B9:M9) -> 340092 | C7: =MAX('Projections Mensuelles'!N9:Y9) -> 781488 | D7: =MAX('Projections Mensuelles'!Z9:AK9) -> 1154142
A8: Revenus totaux (€) | B8: =SUM('Projections Mensuelles'!B12:M12) -> 197663.4 | C8: =SUM('Projections Mensuelles'!N12:Y12) -> 660978.45 | D8: =SUM('Projections Mensuelles'!Z12:AK12) -> 1103399.6
A9: Total coûts (€) | B9: =SUM('Projections Mensuelles'!B18:M18) -> 0 | C9: =SUM('Projections Mensuelles'!N18:Y18) -> 0 | D9: =SUM('Projections Mensuelles'!Z18:AK18) -> 0
A10: EBITDA (€) | B10: =SUM('Projections Mensuelles'!B20:M20) -> 197663.4 | C10: =SUM('Projections Mensuelles'!N20:Y20) -> 660978.45 | D10: =SUM('Projections Mensuelles'!Z20:AK20) -> 1103399.6
A11: Marge EBITDA (%) | B11: =IF(B8>0,B10/B8,"") -> 1 | C11: =IF(C8>0,C10/C8,"") -> 1 | D11: =IF(D8>0,D10/D8,"") -> 1
A12: Locataires (fin de période) | B12: =MAX('Projections Mensuelles'!B23:M23) -> 12600 | C12: =MAX('Projections Mensuelles'!N23:Y23) -> 60600 | D12: =MAX('Projections Mensuelles'!Z23:AK23) -> 108600
A13: LTV estimée (€) | B13: =MAX('Projections Mensuelles'!B25:M25) -> 6030 | C13: =MAX('Projections Mensuelles'!N25:Y25) -> 6030 | D13: =MAX('Projections Mensuelles'!Z25:AK25) -> 6030
A14: LTV / CAC | B14: =MAX('Projections Mensuelles'!B26:M26) -> 0 | C14: =MAX('Projections Mensuelles'!N26:Y26) -> 0 | D14: =MAX('Projections Mensuelles'!Z26:AK26) -> 0
A16: Période | B16: MRR (€) | C16: Agences payantes | D16: EBITDA (€)
A17: M6 | B17: ='Projections Mensuelles'!G8 -> 12663 | C17: ='Projections Mensuelles'!G6 -> 42 | D17: ='Projections Mensuelles'!G20 -> 13929.3
A18: M12 | B18: ='Projections Mensuelles'!M8 -> 28341 | C18: ='Projections Mensuelles'!M6 -> 94 | D18: ='Projections Mensuelles'!M20 -> 31175.1
A19: M18 | B19: ='Projections Mensuelles'!S8 -> 49446 | C19: ='Projections Mensuelles'!S6 -> 164 | D19: ='Projections Mensuelles'!S20 -> 54390.6
A20: M24 | B20: ='Projections Mensuelles'!Y8 -> 65124 | C20: ='Projections Mensuelles'!Y6 -> 216 | D20: ='Projections Mensuelles'!Y20 -> 71636.4
A21: M30 | B21: ='Projections Mensuelles'!AE8 -> 83214 | C21: ='Projections Mensuelles'!AE6 -> 276 | D21: ='Projections Mensuelles'!AE20 -> 91535.4
A22: M36 | B22: ='Projections Mensuelles'!AK8 -> 96178.5 | C22: ='Projections Mensuelles'!AK6 -> 319 | D22: ='Projections Mensuelles'!AK20 -> 105796.35

Sheet Scénarios
A1: COMPARAISON DE SCÉNARIOS — Modifier manuellement pour tester différentes hypothèses
A2: ⚠️ Ce tableau est une copie statique. Pour chaque scénario, modifie les Hypothèses, note les résultats ici, puis compare.
A4: Indicateur | B4: Scénario BASE (deck actuel) | C4: Scénario PESSIMISTE (churn 8%, prix -20%) | D4: Scénario OPTIMISTE (churn 3%, prix +10%) | E4: Mon scénario A | F4: Mon scénario B
A5: ── HYPOTHÈSES ──
A6: Prix Starter (€/mois) | B6: 149 | C6: 119 | D6: 164
A7: Prix Pro (€/mois) | B7: 349 | C7: 279 | D7: 384
A8: Prix Expert (€/mois) | B8: 699 | C8: 559 | D8: 769
A9: Mix Starter / Pro / Expert | B9: 50/35/15 | C9: 55/35/10 | D9: 45/35/20
A10: ARPU pondéré (€) | B10: 249 | C10: 199 | D10: 274
A11: Churn mensuel (%) | B11: 5,0% | C11: 8,0% | D11: 3,0%
A12: CAC (€) | B12: 1500 | C12: 2000 | D12: 1200
A13: Croissance M1-M6 (ag/mois) | B13: 8 | C13: 5 | D13: 12
A14: ── RÉSULTATS M36 ──
A15: Agences payantes M36 | B15: 500 | C15: 280 | D15: 750
A16: MRR M36 (€) | B16: 124500 | C16: 55720 | D16: 205500
A17: ARR M36 (€) | B17: 1,49M€ | C17: 0,67M€ | D17: 2,47M€
A18: EBITDA M36 (€) | B18: ~45K€ | C18: ~(20K€) | D18: ~120K€
A19: Seuil de rentabilité | B19: M14 | C19: M20+ | D19: M11
A20: LTV / CAC | B20: 2,5x | C20: 1,5x | D20: 4,2x
A23: Comment utiliser ce tableau : 1) Va dans Hypothèses et change les valeurs (texte bleu) → 2) Copie les résultats de Synthèse Annuelle → 3) Colle ici dans 'Mon scénario A' ou 'B'

Sheet Unit Economics
A1: UNIT ECONOMICS — PAR AGENCE CLIENTE
A3: REVENUS PAR AGENCE
A4: ARPU mensuel pondéré (€) | B4: =Hypothèses!B37 -> 301.5
A5: ARPU annuel (€) | B5: =Hypothèses!B37*12 -> 3618
A7: COÛT D'ACQUISITION
A8: CAC (€) | B8: =Hypothèses!C22 -> 0
A9: Payback period (mois) | B9: =IF(Hypothèses!B37>0,Hypothèses!C22/Hypothèses!B37,"") -> 0
A11: DURÉE DE VIE
A12: Churn mensuel | B12: =Hypothèses!B17 -> 0.05
A13: Durée de vie moyenne (mois) | B13: =IF(Hypothèses!B17>0,1/Hypothèses!B17,"") -> 20
A14: Durée de vie moyenne (ans) | B14: =IF(Hypothèses!B17>0,1/Hypothèses!B17/12,"") -> 1.6666667
A16: LTV & RENTABILITÉ
A17: LTV brute (€) | B17: =IF(Hypothèses!B17>0,Hypothèses!B37/Hypothèses!B17,"") -> 6030
A18: LTV nette (aprés coût var.) | B18: =IF(Hypothèses!B17>0,(Hypothèses!B37-Hypothèses!B37*0.05)/Hypothèses!B17,"") -> 5728.5
A19: LTV / CAC | B19: =IF(Hypothèses!C22>0,IF(Hypothèses!B17>0,Hypothèses!B37/Hypothèses!B17/Hypothèses!C22,""),"")
A20: Marge brute / agence / mois | B20: =Hypothèses!B37*(1-0.05)-Hypothèses!C23*SUMPRODUCT(Hypothèses!B7:B9,Hypothèses!F7:F9) -> 286.425
